multiworks/__init__.py
multiworks/main.py
multiworks-0.2.3.dist-info/LICENSE
multiworks-0.2.3.dist-info/METADATA
multiworks-0.2.3.dist-info/WHEEL
multiworks-0.2.3.dist-info/top_level.txt
multiworks-0.2.3.dist-info/RECORD
