Metadata-Version: 2.1
Name: multiworks
Version: 0.2.3
Summary: Encrypts/decrypts messages and includes games of Rock, Paper, Scissors (RPS) and Snake, Water, Gun (SWG).
Home-page: https://pypi.org/project/multiworks/
Author: Mohammad Sabbir Hosen
Author-email: hellowsabbir@gmail.com
License: MIT
Classifier: Programming Language :: Python :: 3
Classifier: License :: OSI Approved :: MIT License
Classifier: Operating System :: OS Independent
Requires-Python: >=3.6
License-File: LICENSE
